comfit/__init__.py
comfit/bose_einstein_condensate/__init__.py
comfit/bose_einstein_condensate/bose_einstein_condensate.py
comfit/core/__init__.py
comfit/core/base_system.py
comfit/core/base_system_calc.py
comfit/core/base_system_conf.py
comfit/core/base_system_evolve.py
comfit/core/base_system_get.py
comfit/core/base_system_init.py
comfit/core/base_system_plot.py
comfit/nematic_liquid_crystal/__init__.py
comfit/nematic_liquid_crystal/nematic_liquid_crystal.py
comfit/nematic_liquid_crystal/plot_field_velocity_and_director_matplotlib.py
comfit/nematic_liquid_crystal/plot_field_velocity_and_director_plotly.py
comfit/phase_field_crystal/__init__.py
comfit/phase_field_crystal/phase_field_crystal.py
comfit/phase_field_crystal/phase_field_crystal_1d_periodic.py
comfit/phase_field_crystal/phase_field_crystal_2d_square.py
comfit/phase_field_crystal/phase_field_crystal_2d_triangular.py
comfit/phase_field_crystal/phase_field_crystal_3d_body_centered_cubic.py
comfit/phase_field_crystal/phase_field_crystal_3d_face_centered_cubic.py
comfit/phase_field_crystal/phase_field_crystal_3d_simple_cubic.py
comfit/plot/__init__.py
comfit/plot/plot_angle_field_matplotlib.py
comfit/plot/plot_angle_field_plotly.py
comfit/plot/plot_complex_field_in_plane_matplotlib.py
comfit/plot/plot_complex_field_in_plane_plotly.py
comfit/plot/plot_complex_field_matplotlib.py
comfit/plot/plot_complex_field_plotly.py
comfit/plot/plot_field_in_plane_matplotlib.py
comfit/plot/plot_field_in_plane_plotly.py
comfit/plot/plot_field_matplotlib.py
comfit/plot/plot_field_plotly.py
comfit/plot/plot_nodes_matplotlib.py
comfit/plot/plot_nodes_plotly.py
comfit/plot/plot_subplots_matplotlib.py
comfit/plot/plot_subplots_plotly.py
comfit/plot/plot_surface_matplotlib.py
comfit/plot/plot_surface_plotly.py
comfit/plot/plot_vector_field_in_plane_both_plot_libs.py
comfit/plot/plot_vector_field_matplotlib.py
comfit/plot/plot_vector_field_plotly.py
comfit/quantum_mechanics/__init__.py
comfit/quantum_mechanics/quantum_mechanics.py
comfit-1.9.6.dist-info/LICENSE
comfit-1.9.6.dist-info/METADATA
comfit-1.9.6.dist-info/WHEEL
comfit-1.9.6.dist-info/top_level.txt
comfit-1.9.6.dist-info/RECORD
